guifrontend/__init__.py
guifrontend/cli.py
guifrontend/core/__init__.py
guifrontend/core/action_executor.py
guifrontend/core/frontend_controller.py
guifrontend/core/screenshot_manager.py
guifrontend/core/websocket_client.py
guifrontend-0.1.2.dist-info/METADATA
guifrontend-0.1.2.dist-info/WHEEL
guifrontend-0.1.2.dist-info/entry_points.txt
guifrontend-0.1.2.dist-info/top_level.txt
guifrontend-0.1.2.dist-info/RECORD
