Metadata-Version: 2.4
Name: guifrontend
Version: 0.1.2
Summary: A frontend client for the GUI data collection framework.
Author: xiao
Classifier: Programming Language :: Python :: 3
Classifier: Operating System :: OS Independent
Requires-Python: >=3.8
Requires-Dist: websockets==12.0
Requires-Dist: pillow==10.1.0
Requires-Dist: pyautogui==0.9.54
Requires-Dist: pyyaml==6.0.1
Requires-Dist: async-timeout==4.0.3
Requires-Dist: importlib-resources; python_version < "3.9"
Dynamic: author
Dynamic: classifier
Dynamic: description
Dynamic: description-content-type
Dynamic: requires-dist
Dynamic: requires-python
Dynamic: summary
